[
  {
    "firstName": "Robb",
    "lastName": "Block",
    "email": "Gaylord40@yahoo.com",
    "password": "aliquip qui ipsum",
    "description": "pariatur"
  },
  {
    "firstName": "Keshaun",
    "lastName": "Hagenes",
    "email": "Harley_Runte@yahoo.com",
    "password": "laboris",
    "description": "consequat Lorem culpa aliqua"
  },
  {
    "firstName": "Rebekah",
    "lastName": "Anderson",
    "email": "Irwin.Ward20@hotmail.com",
    "password": "exercitation",
    "description": "Excepteur"
  },
  {
    "firstName": "Novella",
    "lastName": "Collier",
    "email": "Clark9@hotmail.com",
    "password": "id consectetur adipisicing esse",
    "description": "Duis laborum aliqua"
  },
  {
    "firstName": "Lemuel",
    "lastName": "Satterfield",
    "email": "Bell.Sauer53@yahoo.com",
    "password": "pariatur dolore nisi",
    "description": "Excepteur minim laborum fugiat ut"
  },
  {
    "firstName": "Arely",
    "lastName": "Orn",
    "email": "Orrin.Wilkinson@gmail.com",
    "password": "fugiat",
    "description": "exercitation ad et quis"
  },
  {
    "firstName": "Frida",
    "lastName": "Jacobson",
    "email": "Fredrick52@gmail.com",
    "password": "ea ut culpa",
    "description": "do consequat dolore labore"
  },
  {
    "firstName": "Kay",
    "lastName": "Howell",
    "email": "Royce.Hagenes24@gmail.com",
    "password": "exercitation non officia mollit",
    "description": "mollit consequat"
  },
  {
    "firstName": "Liam",
    "lastName": "Mosciski",
    "email": "Isidro69@hotmail.com",
    "password": "aute mollit",
    "description": "est eiusmod"
  },
  {
    "firstName": "Catharine",
    "lastName": "Fritsch",
    "email": "Charlotte.Altenwerth19@yahoo.com",
    "password": "dolore fugiat qui nisi est",
    "description": "Excepteur ut occaecat"
  },
  {
    "firstName": "Daniella",
    "lastName": "Heidenreich",
    "email": "Mabelle.Kovacek51@gmail.com",
    "password": "aliqua Excepteur cillum dolore dolor",
    "description": "amet laboris cillum"
  },
  {
    "firstName": "Grady",
    "lastName": "Beier",
    "email": "Logan_Volkman@hotmail.com",
    "password": "aute sunt",
    "description": "deserunt exercitation"
  },
  {
    "firstName": "Bella",
    "lastName": "Kessler",
    "email": "Melyssa_Lakin0@hotmail.com",
    "password": "Excepteur aute magna",
    "description": "dolore eu reprehenderit deserunt"
  },
  {
    "firstName": "Justyn",
    "lastName": "Bernier",
    "email": "Eleanora_Anderson0@hotmail.com",
    "password": "amet sint mollit do est",
    "description": "exercitation irure ut et"
  },
  {
    "firstName": "Rozella",
    "lastName": "Hermiston",
    "email": "Dandre27@yahoo.com",
    "password": "anim cillum incididunt occaecat consequat",
    "description": "occaecat ea amet"
  },
  {
    "firstName": "Esta",
    "lastName": "Feeney",
    "email": "Dorothy45@gmail.com",
    "password": "cillum consequat quis Ut ullamco",
    "description": "nisi irure mollit"
  },
  {
    "firstName": "Arnoldo",
    "lastName": "Stokes",
    "email": "Lacey.Langosh83@yahoo.com",
    "password": "ea fugiat id culpa",
    "description": "anim eiusmod"
  },
  {
    "firstName": "Tom",
    "lastName": "Flatley",
    "email": "Aiden.Fay@gmail.com",
    "password": "Ut minim",
    "description": "adipisicing velit veniam do ad"
  },
  {
    "firstName": "Shaina",
    "lastName": "Bruen",
    "email": "Dejah_Ortiz@yahoo.com",
    "password": "occaecat aliqua",
    "description": "quis dolore ut reprehenderit"
  },
  {
    "firstName": "Maye",
    "lastName": "Schmidt",
    "email": "Autumn_Purdy71@hotmail.com",
    "password": "dolor eu mollit sit aute",
    "description": "Duis in incididunt aute aliquip"
  },
  {
    "firstName": "Luther",
    "lastName": "Paucek",
    "email": "Kaylin_Runolfsdottir95@yahoo.com",
    "password": "ad eiusmod",
    "description": "voluptate dolore consequat sed"
  },
  {
    "firstName": "Sydnee",
    "lastName": "Jenkins",
    "email": "Andreanne79@hotmail.com",
    "password": "irure consequat in",
    "description": "in velit Duis officia"
  },
  {
    "firstName": "Aaliyah",
    "lastName": "Kuvalis",
    "email": "Buddy.Harber22@gmail.com",
    "password": "proident veniam in",
    "description": "velit"
  },
  {
    "firstName": "Carissa",
    "lastName": "Lind",
    "email": "Ardella.Kuphal27@hotmail.com",
    "password": "reprehenderit voluptate labore adipisicing dolore",
    "description": "ut cillum"
  },
  {
    "firstName": "Zechariah",
    "lastName": "Hand",
    "email": "Krystel52@hotmail.com",
    "password": "ut ullamco nulla reprehenderit",
    "description": "consectetur sit aliqua cupidatat"
  },
  {
    "firstName": "Cali",
    "lastName": "Kshlerin",
    "email": "Mallory.Torphy88@hotmail.com",
    "password": "aliqua",
    "description": "minim sed"
  },
  {
    "firstName": "Emery",
    "lastName": "Kunde",
    "email": "Dave_Ebert26@gmail.com",
    "password": "ut deserunt",
    "description": "Duis cupidatat"
  },
  {
    "firstName": "Rachael",
    "lastName": "Maggio",
    "email": "Danika34@hotmail.com",
    "password": "enim amet ea laboris",
    "description": "labore ut nulla ullamco"
  },
  {
    "firstName": "Dannie",
    "lastName": "Mann",
    "email": "Kamren46@hotmail.com",
    "password": "qui culpa fugiat",
    "description": "commodo"
  },
  {
    "firstName": "Carter",
    "lastName": "Sipes",
    "email": "Cyril_Upton@hotmail.com",
    "password": "adipisicing dolore",
    "description": "in ipsum enim"
  },
  {
    "firstName": "Harmony",
    "lastName": "Carroll",
    "email": "Rhoda_Satterfield60@yahoo.com",
    "password": "id Ut in",
    "description": "deserunt esse consequat ex"
  },
  {
    "firstName": "Gideon",
    "lastName": "Weber",
    "email": "Hattie_Bernhard49@gmail.com",
    "password": "culpa qui",
    "description": "commodo quis Ut in"
  },
  {
    "firstName": "Waldo",
    "lastName": "Feest",
    "email": "Rico47@hotmail.com",
    "password": "esse magna sed",
    "description": "eu in ut"
  },
  {
    "firstName": "Elvis",
    "lastName": "Miller",
    "email": "Rahsaan_Goodwin@hotmail.com",
    "password": "culpa amet",
    "description": "cillum minim est aute dolor"
  },
  {
    "firstName": "Nya",
    "lastName": "Nader",
    "email": "Americo58@yahoo.com",
    "password": "ut dolore consectetur",
    "description": "in ullamco velit esse"
  },
  {
    "firstName": "Brandyn",
    "lastName": "Towne",
    "email": "Armani_Purdy@yahoo.com",
    "password": "ea exercitation aliquip sint",
    "description": "magna amet"
  },
  {
    "firstName": "Chanel",
    "lastName": "Goodwin",
    "email": "Matt_Fay78@yahoo.com",
    "password": "quis velit ea dolore voluptate",
    "description": "deserunt id cupidatat ut"
  },
  {
    "firstName": "Vivian",
    "lastName": "Nikolaus",
    "email": "Roxanne.Murazik@hotmail.com",
    "password": "nostrud proident",
    "description": "magna Excepteur est"
  },
  {
    "firstName": "Sidney",
    "lastName": "Durgan",
    "email": "Lorine.Buckridge65@yahoo.com",
    "password": "quis Lorem elit est exercitation",
    "description": "ad ea Excepteur ut ex"
  },
  {
    "firstName": "Elody",
    "lastName": "Morissette",
    "email": "Jayson.Tillman@gmail.com",
    "password": "Excepteur ex et fugiat",
    "description": "non quis consequat"
  },
  {
    "firstName": "Kathlyn",
    "lastName": "Ullrich",
    "email": "Quinton.Nolan@gmail.com",
    "password": "non ad",
    "description": "reprehenderit"
  },
  {
    "firstName": "Dakota",
    "lastName": "Braun",
    "email": "Lon15@yahoo.com",
    "password": "tempor ullamco",
    "description": "sit"
  },
  {
    "firstName": "Matt",
    "lastName": "Homenick",
    "email": "Sherman13@gmail.com",
    "password": "sed",
    "description": "dolore qui id"
  },
  {
    "firstName": "Raina",
    "lastName": "Erdman",
    "email": "Sylvan_Roberts@hotmail.com",
    "password": "irure magna proident dolor ullamco",
    "description": "Duis"
  },
  {
    "firstName": "Aliyah",
    "lastName": "Lang",
    "email": "Luther.Bernier@yahoo.com",
    "password": "Duis deserunt do commodo",
    "description": "nulla incididunt culpa sit ut"
  },
  {
    "firstName": "Sid",
    "lastName": "Ruecker",
    "email": "Talon_Pfannerstill23@hotmail.com",
    "password": "do",
    "description": "occaecat nulla ea et"
  },
  {
    "firstName": "Nichole",
    "lastName": "Roob",
    "email": "Jessy29@yahoo.com",
    "password": "deserunt aliqua",
    "description": "dolore culpa nostrud sit do"
  },
  {
    "firstName": "Ernestine",
    "lastName": "Upton",
    "email": "Effie15@hotmail.com",
    "password": "nostrud nisi reprehenderit",
    "description": "do consequat ut irure esse"
  },
  {
    "firstName": "Willie",
    "lastName": "Kihn",
    "email": "Ramon_Lindgren@gmail.com",
    "password": "consectetur in dolore in",
    "description": "tempor"
  },
  {
    "firstName": "Nathanial",
    "lastName": "Jaskolski",
    "email": "Alvena.Rutherford@gmail.com",
    "password": "consequat pariatur anim cupidatat",
    "description": "ad irure cupidatat cillum"
  },
  {
    "firstName": "Cale",
    "lastName": "Ullrich",
    "email": "Myrtle_OConnell92@yahoo.com",
    "password": "dolor consequat",
    "description": "in"
  },
  {
    "firstName": "Georgette",
    "lastName": "Reynolds",
    "email": "Grady_McCullough@yahoo.com",
    "password": "tempor incididunt in",
    "description": "ad in aute"
  },
  {
    "firstName": "Devante",
    "lastName": "Terry",
    "email": "Stevie70@yahoo.com",
    "password": "veniam labore Lorem et esse",
    "description": "dolore"
  },
  {
    "firstName": "Hertha",
    "lastName": "Ebert",
    "email": "Madyson.Walsh23@gmail.com",
    "password": "adipisicing Excepteur cillum",
    "description": "deserunt aute"
  },
  {
    "firstName": "Gilberto",
    "lastName": "Beier",
    "email": "Euna20@gmail.com",
    "password": "consequat",
    "description": "aliqua Excepteur veniam nostrud reprehenderit"
  },
  {
    "firstName": "Brad",
    "lastName": "Reinger",
    "email": "Johanna.Ondricka@gmail.com",
    "password": "aliquip elit ullamco enim",
    "description": "ea labore dolore consequat veniam"
  },
  {
    "firstName": "Mallory",
    "lastName": "Barrows",
    "email": "Perry.Wolff14@gmail.com",
    "password": "ad pariatur aliquip dolor adipisicing",
    "description": "dolore"
  },
  {
    "firstName": "Margarete",
    "lastName": "Koelpin",
    "email": "Daisy.Abbott@yahoo.com",
    "password": "labore minim sit",
    "description": "enim reprehenderit"
  },
  {
    "firstName": "Helene",
    "lastName": "Vandervort",
    "email": "Lyric99@yahoo.com",
    "password": "nostrud aliqua Duis",
    "description": "fugiat velit enim Duis irure"
  },
  {
    "firstName": "Kelli",
    "lastName": "Kemmer",
    "email": "Elian_Hudson68@gmail.com",
    "password": "Lorem incididunt ullamco consectetur",
    "description": "Excepteur in"
  },
  {
    "firstName": "Darby",
    "lastName": "Sauer",
    "email": "Genesis_Mohr@gmail.com",
    "password": "voluptate",
    "description": "ex Duis dolor aliquip qui"
  },
  {
    "firstName": "Nasir",
    "lastName": "O'Keefe",
    "email": "Alvis18@yahoo.com",
    "password": "nisi consectetur occaecat amet sint",
    "description": "aute ad sed cillum laboris"
  },
  {
    "firstName": "Clay",
    "lastName": "Schiller",
    "email": "Bart60@yahoo.com",
    "password": "culpa eu",
    "description": "est esse ad dolore"
  },
  {
    "firstName": "Cathrine",
    "lastName": "Zulauf",
    "email": "Kiara81@yahoo.com",
    "password": "reprehenderit",
    "description": "quis"
  },
  {
    "firstName": "Lafayette",
    "lastName": "Oberbrunner",
    "email": "Lia13@hotmail.com",
    "password": "dolor in culpa dolore ad",
    "description": "amet"
  },
  {
    "firstName": "Reymundo",
    "lastName": "Murphy",
    "email": "Caroline82@yahoo.com",
    "password": "nostrud in",
    "description": "exercitation aliquip"
  },
  {
    "firstName": "Celestino",
    "lastName": "Reynolds",
    "email": "Jordane_Terry31@gmail.com",
    "password": "voluptate minim labore dolor",
    "description": "minim officia elit ex dolore"
  },
  {
    "firstName": "Cheyanne",
    "lastName": "Eichmann",
    "email": "Noah.Ryan52@hotmail.com",
    "password": "officia nostrud",
    "description": "et Duis nostrud Ut dolore"
  },
  {
    "firstName": "Jessy",
    "lastName": "Braun",
    "email": "Leanne3@gmail.com",
    "password": "in nostrud elit officia",
    "description": "occaecat"
  },
  {
    "firstName": "Claudine",
    "lastName": "Hagenes",
    "email": "Kathryne.Veum@hotmail.com",
    "password": "deserunt commodo et",
    "description": "adipisicing ipsum laboris"
  },
  {
    "firstName": "Piper",
    "lastName": "Upton",
    "email": "Janet_Zieme@hotmail.com",
    "password": "sint aliqua dolore commodo qui",
    "description": "exercitation consequat sed elit ad"
  },
  {
    "firstName": "Karolann",
    "lastName": "Upton",
    "email": "Orville_Wolf50@hotmail.com",
    "password": "Ut ut",
    "description": "veniam occaecat eiusmod"
  },
  {
    "firstName": "Pink",
    "lastName": "Brekke",
    "email": "Emmanuel27@yahoo.com",
    "password": "culpa sed",
    "description": "in sint occaecat"
  },
  {
    "firstName": "Maynard",
    "lastName": "Leffler",
    "email": "Harley.Hickle@yahoo.com",
    "password": "sint ut quis reprehenderit dolore",
    "description": "veniam laboris irure"
  },
  {
    "firstName": "Kattie",
    "lastName": "Kling",
    "email": "Laura.Barton@yahoo.com",
    "password": "eiusmod veniam nulla magna",
    "description": "Ut cupidatat nulla"
  },
  {
    "firstName": "Hollis",
    "lastName": "Kilback",
    "email": "Albin11@yahoo.com",
    "password": "anim tempor sed",
    "description": "commodo ex ut ut"
  },
  {
    "firstName": "Donato",
    "lastName": "Schowalter",
    "email": "Elyssa_Wiegand95@gmail.com",
    "password": "sunt",
    "description": "dolore voluptate"
  },
  {
    "firstName": "Norval",
    "lastName": "Wintheiser",
    "email": "Janae.Kshlerin@hotmail.com",
    "password": "Ut adipisicing anim deserunt",
    "description": "dolor"
  },
  {
    "firstName": "Lou",
    "lastName": "DuBuque",
    "email": "Paula94@gmail.com",
    "password": "in ut",
    "description": "magna"
  },
  {
    "firstName": "Summer",
    "lastName": "Tillman",
    "email": "Crystal17@yahoo.com",
    "password": "ea pariatur do",
    "description": "ex occaecat Ut magna anim"
  },
  {
    "firstName": "Gilbert",
    "lastName": "Weimann",
    "email": "Axel67@hotmail.com",
    "password": "in",
    "description": "Duis veniam nisi occaecat"
  },
  {
    "firstName": "Maya",
    "lastName": "Runolfsson",
    "email": "Colt_Grimes@yahoo.com",
    "password": "enim Lorem",
    "description": "non"
  },
  {
    "firstName": "Hadley",
    "lastName": "Reilly",
    "email": "Rodrigo.Robel70@yahoo.com",
    "password": "officia minim deserunt ut pariatur",
    "description": "dolore Excepteur labore"
  },
  {
    "firstName": "Braden",
    "lastName": "McLaughlin",
    "email": "Donna30@hotmail.com",
    "password": "veniam aliqua culpa officia voluptate",
    "description": "quis nostrud anim consectetur"
  },
  {
    "firstName": "Alejandrin",
    "lastName": "Reynolds",
    "email": "Alta.Sawayn@yahoo.com",
    "password": "pariatur id in in sunt",
    "description": "dolore sit aliqua deserunt dolor"
  },
  {
    "firstName": "Providenci",
    "lastName": "Roberts",
    "email": "Sonya.Hermiston53@hotmail.com",
    "password": "adipisicing laborum anim dolor",
    "description": "et amet"
  },
  {
    "firstName": "Kamren",
    "lastName": "Murray",
    "email": "Marlen.Rutherford33@gmail.com",
    "password": "exercitation",
    "description": "adipisicing Lorem sunt laborum"
  },
  {
    "firstName": "Cassidy",
    "lastName": "Emmerich",
    "email": "Ryann30@yahoo.com",
    "password": "incididunt",
    "description": "consequat occaecat velit"
  },
  {
    "firstName": "Evie",
    "lastName": "Maggio",
    "email": "Alberto76@gmail.com",
    "password": "ea",
    "description": "mollit ad eu esse Lorem"
  },
  {
    "firstName": "Cathy",
    "lastName": "Mante",
    "email": "Justice.Kuphal9@hotmail.com",
    "password": "incididunt",
    "description": "eu aliqua incididunt proident"
  },
  {
    "firstName": "Wendy",
    "lastName": "Graham",
    "email": "Joany_Hansen@hotmail.com",
    "password": "sed qui",
    "description": "in Duis velit"
  },
  {
    "firstName": "Dagmar",
    "lastName": "Padberg",
    "email": "Camron_Walter1@yahoo.com",
    "password": "est labore velit sint nisi",
    "description": "in officia ex"
  },
  {
    "firstName": "Arnoldo",
    "lastName": "Kuhn",
    "email": "Bryce59@yahoo.com",
    "password": "labore irure ea amet",
    "description": "proident laborum"
  },
  {
    "firstName": "Camron",
    "lastName": "Satterfield",
    "email": "Brianne_Kulas65@yahoo.com",
    "password": "sint officia",
    "description": "et non labore Duis"
  },
  {
    "firstName": "Leann",
    "lastName": "Koelpin",
    "email": "Harmon_Fahey@yahoo.com",
    "password": "exercitation",
    "description": "pariatur proident aliquip"
  },
  {
    "firstName": "Braxton",
    "lastName": "Brakus",
    "email": "Grover.Bins27@yahoo.com",
    "password": "dolor",
    "description": "fugiat deserunt reprehenderit"
  },
  {
    "firstName": "Hildegard",
    "lastName": "Grant",
    "email": "Solon_Johnson30@hotmail.com",
    "password": "do nisi ex proident",
    "description": "id"
  },
  {
    "firstName": "Rodger",
    "lastName": "Rath",
    "email": "Rubye7@gmail.com",
    "password": "est aliquip esse sunt pariatur",
    "description": "dolore"
  },
  {
    "firstName": "Brayan",
    "lastName": "Gutkowski",
    "email": "Marshall.Stamm32@gmail.com",
    "password": "nulla dolor",
    "description": "Lorem in sunt aliquip Duis"
  },
  {
    "firstName": "Nia",
    "lastName": "Heaney",
    "email": "Gwendolyn.Mosciski@yahoo.com",
    "password": "laboris cupidatat",
    "description": "incididunt Duis non laborum"
  }
]
